setup.py
csdl/__init__.py
csdl/csdl.py
csdl/test.py
csdl.egg-info/PKG-INFO
csdl.egg-info/SOURCES.txt
csdl.egg-info/dependency_links.txt
csdl.egg-info/requires.txt
csdl.egg-info/top_level.txt