Metadata-Version: 1.0
Name: csdl
Version: 0.1
Summary: Cross Stiched Spectral Density
Home-page: https://github.com/jordens/csdl
Author: Robert Jordens
Author-email: jordens@gmail.com
License: BSD
Platform: UNKNOWN
